my_pr/util.py
mypr-1.0.dist-info/METADATA
mypr-1.0.dist-info/WHEEL
mypr-1.0.dist-info/top_level.txt
mypr-1.0.dist-info/RECORD
