Metadata-Version: 2.1
Name: mypr
Version: 1.0
Summary: Python Project
Home-page: https://pypi.org/manage/projects/
Author: sneha
Author-email: sneha@gmail.com
License: UNKNOWN
Platform: UNKNOWN
